Metadata-Version: 1.0
Name: pedigree
Version: 1.1.0
Summary: Store family trees in plain text and visualize them in your browser
Home-page: https://github.com/jbaber/pedigree
Author: John Baber-Lucero
Author-email: python@frundle.com
License: GPL
Platform: UNKNOWN
